.testr.conf
.travis.yml
AUTHORS
CONTRIBUTING.md
COPYING
MANIFEST.in
Makefile
NEWS
README.md
README.swift.md
TODO
appveyor.yml
dulwich.cfg
setup.cfg
setup.py
tox.ini
bin/dul-receive-pack
bin/dul-upload-pack
bin/dulwich
docs/Makefile
docs/conf.py
docs/index.txt
docs/make.bat
docs/performance.txt
docs/protocol.txt
docs/tutorial/Makefile
docs/tutorial/conclusion.txt
docs/tutorial/encoding.txt
docs/tutorial/file-format.txt
docs/tutorial/index.txt
docs/tutorial/introduction.txt
docs/tutorial/object-store.txt
docs/tutorial/porcelain.txt
docs/tutorial/remote.txt
docs/tutorial/repo.txt
docs/tutorial/tag.txt
dulwich/__init__.py
dulwich/archive.py
dulwich/client.py
dulwich/config.py
dulwich/diff_tree.py
dulwich/errors.py
dulwich/fastexport.py
dulwich/file.py
dulwich/greenthreads.py
dulwich/hooks.py
dulwich/ignore.py
dulwich/index.py
dulwich/log_utils.py
dulwich/lru_cache.py
dulwich/object_store.py
dulwich/objects.py
dulwich/objectspec.py
dulwich/pack.py
dulwich/patch.py
dulwich/porcelain.py
dulwich/protocol.py
dulwich/reflog.py
dulwich/refs.py
dulwich/repo.py
dulwich/server.py
dulwich/stdint.h
dulwich/walk.py
dulwich/web.py
dulwichTest.egg-info/PKG-INFO
dulwichTest.egg-info/SOURCES.txt
dulwichTest.egg-info/dependency_links.txt
dulwichTest.egg-info/top_level.txt
dulwich/contrib/__init__.py
dulwich/contrib/paramiko_vendor.py
dulwich/contrib/release_robot.py
dulwich/contrib/swift.py
dulwich/contrib/test_release_robot.py
dulwich/contrib/test_swift.py
dulwich/contrib/test_swift_smoke.py
dulwich/tests/__init__.py
dulwich/tests/test_archive.py
dulwich/tests/test_blackbox.py
dulwich/tests/test_client.py
dulwich/tests/test_config.py
dulwich/tests/test_diff_tree.py
dulwich/tests/test_fastexport.py
dulwich/tests/test_file.py
dulwich/tests/test_grafts.py
dulwich/tests/test_greenthreads.py
dulwich/tests/test_hooks.py
dulwich/tests/test_ignore.py
dulwich/tests/test_index.py
dulwich/tests/test_lru_cache.py
dulwich/tests/test_missing_obj_finder.py
dulwich/tests/test_object_store.py
dulwich/tests/test_objects.py
dulwich/tests/test_objectspec.py
dulwich/tests/test_pack.py
dulwich/tests/test_patch.py
dulwich/tests/test_porcelain.py
