Metadata-Version: 1.1
Name: dulwichTest
Version: 0.18.7
Summary: Python Git Library
Home-page: https://www.dulwich.io/
Author: UNKNOWN
Author-email: jelmer@jelmer.uk
License: Apachev2 or later or GPLv2
Keywords: git
Platform: UNKNOWN
Classifier: Development Status :: 4 - Beta
Classifier: License :: OSI Approved :: Apache Software License
Classifier: Programming Language :: Python :: 2.7
Classifier: Programming Language :: Python :: 3.3
Classifier: Programming Language :: Python :: 3.4
Classifier: Programming Language :: Python :: 3.5
Classifier: Programming Language :: Python :: 3.6
Classifier: Programming Language :: Python :: Implementation :: CPython
Classifier: Programming Language :: Python :: Implementation :: PyPy
Classifier: Operating System :: POSIX
Classifier: Operating System :: Microsoft :: Windows
Classifier: Topic :: Software Development :: Version Control
